Metadata-Version: 2.1
Name: py-open-fonts
Version: 0.6.5
Summary: A collection of beautiful free and open source fonts.
Home-page: https://github.com/kiwi0fruit/py-open-fonts
Author: kiwi0fruit
Author-email: peter.zagubisalo@gmail.com
License: Aggregate (MIT, Apache-2.0, OFL-1.1, Public-Domain, DejaVu-Fonts)
Platform: UNKNOWN
Classifier: Development Status :: 3 - Alpha
Classifier: Topic :: Software Development :: Build Tools
Classifier: Programming Language :: Python :: 3
Classifier: Programming Language :: Python :: 3.6
Classifier: License :: OSI Approved :: MIT License
Classifier: License :: OSI Approved :: Apache Software License
Classifier: License :: OSI Approved :: SIL Open Font License 1.1 (OFL-1.1)
Classifier: License :: Public Domain
Requires-Python: >=3.6
